anakin_ai/__init__.py
anakin_ai/client.py
anakin_ai-0.1.4.dist-info/METADATA
anakin_ai-0.1.4.dist-info/WHEEL
anakin_ai-0.1.4.dist-info/licenses/LICENSE
anakin_ai-0.1.4.dist-info/RECORD
