Metadata-Version: 2.3
Name: anakin-ai
Version: 0.1.4
Summary: A Python client for interacting with the Anakin AI API
Project-URL: Homepage, https://anakin.ai
Project-URL: Bug Tracker, https://github.com/lynn-mikami/anakin-ai-unofficial-api/issues
Author-email: Lynn Mikami <lgreenwood288@gmail.com>
License-File: LICENSE
Classifier: License :: OSI Approved :: MIT License
Classifier: Operating System :: OS Independent
Classifier: Programming Language :: Python :: 3
Requires-Python: >=3.7
Requires-Dist: requests>=2.25.1
